query_ec2_metadata.py
query_ec2_metadata-0.1.3.dist-info/entry_points.txt
query_ec2_metadata-0.1.3.dist-info/LICENSE
query_ec2_metadata-0.1.3.dist-info/WHEEL
query_ec2_metadata-0.1.3.dist-info/METADATA
query_ec2_metadata-0.1.3.dist-info/RECORD
