Metadata-Version: 2.1
Name: query-ec2-metadata
Version: 0.1.3
Summary: Allows querying EC2 instance metadata
Home-page: https://github.com/hmrc/ec2_metadata
License: Apache-2.0
Author: HMRC WebOps
Requires-Python: >=3.6.2,<4.0
Classifier: License :: OSI Approved :: Apache Software License
Classifier: Programming Language :: Python :: 3
Classifier: Programming Language :: Python :: 3.7
Classifier: Programming Language :: Python :: 3.8
Classifier: Programming Language :: Python :: 3.9
Requires-Dist: requests (>=2.25.1,<3.0.0)
Project-URL: Repository, https://github.com/hmrc/ec2_metadata
